primalhelper/__init__.py
primalhelper/bedfile.py
primalhelper/cli.py
primalhelper/consensus_remap.py
primalhelper/hamming_remap.py
primalhelper/legacy.py
primalhelper/remove_terminal_n.py
primalhelper-1.0.1.dist-info/METADATA
primalhelper-1.0.1.dist-info/WHEEL
primalhelper-1.0.1.dist-info/entry_points.txt
primalhelper-1.0.1.dist-info/RECORD
