Metadata-Version: 2.1
Name: primalhelper
Version: 1.0.1
Summary: 
Author: ChrisKent
Author-email: chrisgkent@gmail.com
Requires-Python: >=3.11,<4.0
Classifier: Programming Language :: Python :: 3
Classifier: Programming Language :: Python :: 3.11
Requires-Dist: typer[all] (>=0.9.0,<0.10.0)
